signal_ICT_DarshilSapara_92400133027/__init__.py
signal_ICT_DarshilSapara_92400133027/operations.py
signal_ICT_DarshilSapara_92400133027/trigonometric_signals.py
signal_ICT_DarshilSapara_92400133027/unitary_signals.py
signal_ict_darshilsapara_92400133027-0.1.dist-info/METADATA
signal_ict_darshilsapara_92400133027-0.1.dist-info/WHEEL
signal_ict_darshilsapara_92400133027-0.1.dist-info/top_level.txt
signal_ict_darshilsapara_92400133027-0.1.dist-info/RECORD
