Metadata-Version: 2.4
Name: signal_ICT_DarshilSapara_92400133027
Version: 0.1
Summary: Signal generation and operations package for ICT assignment
Author: Darshil Sapara
Author-email: darshil.sapara133633@marwadiuniversity.ac.in
Requires-Dist: numpy
Requires-Dist: matplotlib
Dynamic: author
Dynamic: author-email
Dynamic: requires-dist
Dynamic: summary
